pymorphy2_dicts_ru/__init__.py
pymorphy2_dicts_ru/version.py
pymorphy2_dicts_ru/data/grammemes.json
pymorphy2_dicts_ru/data/gramtab-opencorpora-ext.json
pymorphy2_dicts_ru/data/gramtab-opencorpora-int.json
pymorphy2_dicts_ru/data/meta.json
pymorphy2_dicts_ru/data/p_t_given_w.intdawg
pymorphy2_dicts_ru/data/paradigms.array
pymorphy2_dicts_ru/data/prediction-suffixes-0.dawg
pymorphy2_dicts_ru/data/prediction-suffixes-1.dawg
pymorphy2_dicts_ru/data/prediction-suffixes-2.dawg
pymorphy2_dicts_ru/data/suffixes.json
pymorphy2_dicts_ru/data/words.dawg
pymorphy2_dicts_ru-2.4.417127.4579844.dist-info/METADATA
pymorphy2_dicts_ru-2.4.417127.4579844.dist-info/WHEEL
pymorphy2_dicts_ru-2.4.417127.4579844.dist-info/entry_points.txt
pymorphy2_dicts_ru-2.4.417127.4579844.dist-info/pbr.json
pymorphy2_dicts_ru-2.4.417127.4579844.dist-info/top_level.txt
pymorphy2_dicts_ru-2.4.417127.4579844.dist-info/RECORD
